address_converter/__init__.py
address_converter/converter.py
address_converter-0.1.1.dist-info/licenses/LICENSE
address_converter-0.1.1.dist-info/METADATA
address_converter-0.1.1.dist-info/WHEEL
address_converter-0.1.1.dist-info/top_level.txt
address_converter-0.1.1.dist-info/RECORD
