Metadata-Version: 2.4
Name: address-converter
Version: 0.1.1
Summary: A lightweight converter for blockchain addresses supporting multiple formats
Author-email: dongzhenye <dongzhenye@gmail.com>
Project-URL: Homepage, https://github.com/dongzhenye/address-converter
Project-URL: Bug Tracker, https://github.com/dongzhenye/address-converter/issues
Classifier: Development Status :: 4 - Beta
Classifier: Intended Audience :: Developers
Classifier: License :: OSI Approved :: MIT License
Classifier: Programming Language :: Python :: 3
Classifier: Programming Language :: Python :: 3.7
Classifier: Programming Language :: Python :: 3.8
Classifier: Programming Language :: Python :: 3.9
Classifier: Programming Language :: Python :: 3.10
Requires-Python: >=3.7
License-File: LICENSE
Requires-Dist: base58>=2.0.0
Dynamic: license-file
